sputnik/SpuBase.py
sputnik/SpuCache.py
sputnik/SpuCacheManager.py
sputnik/SpuCacheMonitor.py
sputnik/SpuCacheObject.py
sputnik/SpuCallTracker.py
sputnik/SpuCeleryCache.py
sputnik/SpuConfig.py
sputnik/SpuContext.py
sputnik/SpuCountCache.py
sputnik/SpuCountServer.py
sputnik/SpuDB.py
sputnik/SpuDBObject.py
sputnik/SpuDBObjectCache.py
sputnik/SpuDBObjectProfile.py
sputnik/SpuDBObjectShort.py
sputnik/SpuDataFormat.py
sputnik/SpuDateTime.py
sputnik/SpuDebug.py
sputnik/SpuDocCache.py
sputnik/SpuDomainManager.py
sputnik/SpuError.py
sputnik/SpuException.py
sputnik/SpuFS.py
sputnik/SpuFactory.py
sputnik/SpuFastMQ.py
sputnik/SpuFieldFilter.py
sputnik/SpuGeohash.py
sputnik/SpuGis.py
sputnik/SpuHook.py
sputnik/SpuHttpClient.py
sputnik/SpuIS.py
sputnik/SpuIdGraph.py
sputnik/SpuImage.py
sputnik/SpuJson.py
sputnik/SpuLogging.py
sputnik/SpuMongoDBObject.py
sputnik/SpuProfile.py
sputnik/SpuPythonObject.py
sputnik/SpuRedis.py
sputnik/SpuRequest.py
sputnik/SpuSQLRollback.py
sputnik/SpuSearch.py
sputnik/SpuSession.py
sputnik/SpuSound.py
sputnik/SpuSys.py
sputnik/SpuTableCache.py
sputnik/SpuUIModuleLoad.py
sputnik/SpuUOM.py
sputnik/SpuUrl.py
sputnik/SpuUtil.py
sputnik/SpuVectorCache.py
sputnik/Sputnik.py
sputnik/__init__.py
sputnik/upyun.py
sputnik/thirdparty/QClient.py
sputnik/thirdparty/__init__.py
sputnik/thirdparty/openqqpy.py
sputnik/thirdparty/sphinxapi.py
sputnik/thirdparty/weibo.py
sputnik/thirdparty/new_weibopy/__init__.py
sputnik/thirdparty/new_weibopy/weibo.py
sputnik/thirdparty/new_weibopy/weibo1.py
sputnik/thirdparty/qqweibo/__init__.py
sputnik/thirdparty/qqweibo/api.py
sputnik/thirdparty/qqweibo/auth.py
sputnik/thirdparty/qqweibo/binder.py
sputnik/thirdparty/qqweibo/cache.py
sputnik/thirdparty/qqweibo/compat.py
sputnik/thirdparty/qqweibo/error.py
sputnik/thirdparty/qqweibo/models.py
sputnik/thirdparty/qqweibo/oauth.py
sputnik/thirdparty/qqweibo/parsers.py
sputnik/thirdparty/qqweibo/utils.py
sputnik/thirdparty/tweibo/__init__.py
sputnik/thirdparty/tweibo/oauth.py
sputnik_web-0.5.6.dist-info/LICENSE
sputnik_web-0.5.6.dist-info/METADATA
sputnik_web-0.5.6.dist-info/WHEEL
sputnik_web-0.5.6.dist-info/top_level.txt
sputnik_web-0.5.6.dist-info/RECORD
