Metadata-Version: 2.1
Name: sputnik-web
Version: 0.5.6
Summary: sputnik is web framework
Home-page: https://github.com/cognboun/sputnik
Author: cognboun
Author-email: cognboun@gmail.com
License: BSD License
Project-URL: Source, https://github.com/cognboun/sputnik
Platform: all
Classifier: Intended Audience :: Developers
Classifier: Operating System :: OS Independent
Classifier: Natural Language :: Chinese (Simplified)
Classifier: Programming Language :: Python
Classifier: Programming Language :: Python :: 2
Classifier: Programming Language :: Python :: 2.7
Classifier: Programming Language :: Python :: 3
Classifier: Programming Language :: Python :: 3.5
Classifier: Programming Language :: Python :: 3.6
Classifier: Programming Language :: Python :: 3.7
Classifier: Programming Language :: Python :: 3.8
Classifier: Topic :: Software Development :: Libraries
License-File: LICENSE
Requires-Dist: arrow >=1.1.0
Requires-Dist: requests >=2.20.1
Requires-Dist: pymongo ==2.6.1
Requires-Dist: pyzmq ==14.4.1
Requires-Dist: redis ==2.10.3
Requires-Dist: requests ==2.8.1
Requires-Dist: thrift ==0.9.1
Requires-Dist: tornado ==2.1.1
Requires-Dist: event-time-format >=1.0.2
